segno_pil.py
segno_pil-1.0.0.dist-info/LICENSE.txt
segno_pil-1.0.0.dist-info/METADATA
segno_pil-1.0.0.dist-info/WHEEL
segno_pil-1.0.0.dist-info/entry_points.txt
segno_pil-1.0.0.dist-info/top_level.txt
segno_pil-1.0.0.dist-info/RECORD
