Metadata-Version: 2.1
Name: segno-pil
Version: 1.0.0
Summary: PIL/Pillow plugin for the Segno (Micro) QR Code generator
Home-page: https://github.com/heuer/segno-pil/
Author: Lars Heuer
Author-email: heuer@semagia.com
License: BSD
Keywords: QR Code,Micro QR Code,ISO/IEC 18004,ISO/IEC 18004:2006(E),ISO/IEC 18004:2015(E),PIL,Pillow
Platform: any
Classifier: Development Status :: 4 - Beta
Classifier: Intended Audience :: Developers
Classifier: License :: OSI Approved :: BSD License
Classifier: Operating System :: OS Independent
Classifier: Programming Language :: Python
Classifier: Programming Language :: Python :: 2
Classifier: Programming Language :: Python :: 2.7
Classifier: Programming Language :: Python :: 3
Classifier: Programming Language :: Python :: 3.7
Classifier: Topic :: Multimedia :: Graphics
Classifier: Topic :: Printing
Classifier: Topic :: Software Development :: Libraries :: Python Modules
Classifier: Topic :: Utilities
Requires-Dist: Pillow
Requires-Dist: segno
